Workbook

Sheet Read Me
B2: Information Security Risk Assessment — NorthStar Lending (NIST CSF 2.0)
B3: Fictional fintech. Lab project demonstrating a GRC risk-assessment workflow in Excel.
B6: How this workbook works
B7: Risk Register | C7: The source of truth. Each risk is scored Likelihood x Impact (1-5) before controls (Inherent) and after controls (Residual).
C8: Inherent Score, Residual Score, and Residual Level are live FORMULAS — change a Likelihood or Impact and everything updates.
B9: Risk Heatmap | C9: 5x5 grid counting residual risks by Likelihood x Impact. Cells are colored by risk band.
B10: Dashboard | C10: Counts by risk level and CSF function, with a chart.
B11: Quantitative (SLE-ALE) | C11: Annualized-loss model for a top risk — translates risk into dollars to justify control spend.
B13: Risk bands | C13: Score = Likelihood x Impact | F13: Low 1-4 | Moderate 5-9 | High 10-14 | Critical 15-25
B14: Method | C14: Semi-quantitative, aligned to NIST SP 800-30.
B15: Prepared by | C15: Salim Mbaye

Sheet Risk Register
A1: Risk ID | B1: Risk Title | C1: CSF Function | D1: Threat Source | E1: Vulnerability | F1: Asset Affected | G1: Inh. L | H1: Inh. I | I1: Inherent Score | J1: Existing Controls | K1: Control Effectiveness | L1: Res. L | M1: Res. I | N1: Residual Score | O1: Residual Level | P1: Risk Owner | Q1: Treatment | R1: Recommended Controls
A2: R01 | B2: Phishing leads to credential compromise | C2: PR | D2: External attacker | E2: Staff susceptible to phishing; inconsistent security awareness training | F2: A7 Endpoints / A8 Identity Provider | G2: 5 | H2: 4 | I2: =G2*H2 -> 20 | J2: Email filtering; annual security training | K2: Moderate | L2: 3 | M2: 4 | N2: =L2*M2 -> 12 | O2: =IF(N2<=4,"Low",IF(N2<=9,"Moderate",IF(N2<=14,"High","Critical"))) -> High | P2: Security Lead | Q2: Mitigate | R2: Phishing-resistant MFA; quarterly phishing simulations; targeted training
A3: R02 | B3: Missing MFA on admin and SSO accounts | C3: PR | D3: External attacker / credential theft | E3: Administrative and SSO accounts do not enforce MFA | F3: A8 Identity Provider | G3: 4 | H3: 5 | I3: =G3*H3 -> 20 | J3: SSO deployed; MFA optional/not enforced | K3: Low | L3: 3 | M3: 5 | N3: =L3*M3 -> 15 | O3: =IF(N3<=4,"Low",IF(N3<=9,"Moderate",IF(N3<=14,"High","Critical"))) -> Critical | P3: IT & Security | Q3: Mitigate | R3: Enforce phishing-resistant MFA on all admin and SSO accounts
A4: R03 | B4: Insecure customer API exposes financial data | C4: PR | D4: External attacker | E4: Loan portal APIs lack strong authN/authZ and rate limiting | F4: A1 Borrower Portal | G4: 4 | H4: 5 | I4: =G4*H4 -> 20 | J4: TLS in transit; basic API keys | K4: Low | L4: 3 | M4: 5 | N4: =L4*M4 -> 15 | O4: =IF(N4<=4,"Low",IF(N4<=9,"Moderate",IF(N4<=14,"High","Critical"))) -> Critical | P4: Engineering Lead | Q4: Mitigate | R4: OAuth2 + authz checks; rate limiting; WAF; API gateway
A5: R04 | B5: Ransomware disrupts operations and data | C5: PR | D5: Cybercriminal group | E5: Flat network, inconsistent patching, untested backups | F5: A4 Customer DB / A7 Endpoints | G5: 3 | H5: 5 | I5: =G5*H5 -> 15 | J5: EDR on some endpoints; cloud backups exist | K5: Moderate | L5: 2 | M5: 5 | N5: =L5*M5 -> 10 | O5: =IF(N5<=4,"Low",IF(N5<=9,"Moderate",IF(N5<=14,"High","Critical"))) -> High | P5: IT | Q5: Mitigate | R5: EDR on all endpoints; network segmentation; tested immutable backups
A6: R05 | B6: Unencrypted sensitive data at rest | C6: PR | D6: Insider / external attacker | E6: Some S3 buckets and data exports not encrypted; inconsistent key mgmt | F6: A5 Cloud Storage (S3) | G6: 3 | H6: 5 | I6: =G6*H6 -> 15 | J6: RDS encryption enabled; S3 inconsistent | K6: Moderate | L6: 2 | M6: 5 | N6: =L6*M6 -> 10 | O6: =IF(N6<=4,"Low",IF(N6<=9,"Moderate",IF(N6<=14,"High","Critical"))) -> High | P6: Cloud Engineering | Q6: Mitigate | R6: Enforce encryption-at-rest org-wide; central KMS; block unencrypted writes
A7: R06 | B7: Misconfigured cloud storage (public buckets) | C7: PR | D7: External attacker | E7: No guardrails preventing public buckets; no cloud posture monitoring | F7: A5 Cloud Storage (S3) | G7: 3 | H7: 5 | I7: =G7*H7 -> 15 | J7: Manual periodic reviews | K7: Low | L7: 3 | M7: 5 | N7: =L7*M7 -> 15 | O7: =IF(N7<=4,"Low",IF(N7<=9,"Moderate",IF(N7<=14,"High","Critical"))) -> Critical | P7: Cloud Engineering | Q7: Mitigate | R7: Enable Block Public Access; deploy CSPM; scan IaC before deploy
A8: R07 | B8: Third-party / vendor breach | C8: GV | D8: Vendor / subprocessor compromise | E8: No formal vendor risk management or vendor inventory | F8: A6 Corporate SaaS | G8: 3 | H8: 4 | I8: =G8*H8 -> 12 | J8: Ad-hoc vendor selection | K8: Low | L8: 3 | M8: 4 | N8: =L8*M8 -> 12 | O8: =IF(N8<=4,"Low",IF(N8<=9,"Moderate",IF(N8<=14,"High","Critical"))) -> High | P8: GRC & Procurement | Q8: Mitigate | R8: Vendor risk program; security questionnaires; DPAs; review vendor SOC 2
A9: R08 | B9: Insider misuse of customer financial data | C9: PR | D9: Malicious or negligent insider | E9: Over-broad access; no least privilege; limited user monitoring | F9: A2 Underwriting / A4 Customer DB | G9: 2 | H9: 5 | I9: =G9*H9 -> 10 | J9: Partial role-based access | K9: Moderate | L9: 2 | M9: 4 | N9: =L9*M9 -> 8 | O9: =IF(N9<=4,"Low",IF(N9<=9,"Moderate",IF(N9<=14,"High","Critical"))) -> Moderate | P9: Security Lead | Q9: Mitigate | R9: Least privilege; periodic access reviews; DLP; user-activity monitoring
A10: R09 | B10: Inadequate logging and monitoring | C10: DE | D10: Any threat source | E10: No centralized logging or SIEM; detection coverage gaps | F10: All in-scope systems | G10: 4 | H10: 4 | I10: =G10*H10 -> 16 | J10: Some cloud logs retained | K10: Low | L10: 3 | M10: 4 | N10: =L10*M10 -> 12 | O10: =IF(N10<=4,"Low",IF(N10<=9,"Moderate",IF(N10<=14,"High","Critical"))) -> High | P10: Security Lead | Q10: Mitigate | R10: Centralized logging; SIEM with alerting; defined log-retention policy
A11: R10 | B11: No formal incident response plan | C11: RS | D11: Any threat source | E11: No documented IR plan, defined roles, or testing | F11: All in-scope systems | G11: 3 | H11: 5 | I11: =G11*H11 -> 15 | J11: Informal escalation only | K11: None | L11: 3 | M11: 5 | N11: =L11*M11 -> 15 | O11: =IF(N11<=4,"Low",IF(N11<=9,"Moderate",IF(N11<=14,"High","Critical"))) -> Critical | P11: GRC & Security | Q11: Mitigate | R11: Documented IR plan; roles & runbooks; annual tabletop exercises
A12: R11 | B12: GLBA Safeguards program gaps | C12: GV | D12: Regulatory / examiner | E12: No written security program, risk-assessment cadence, or designated Qualified Individual | F12: Organization-wide | G12: 4 | H12: 4 | I12: =G12*H12 -> 16 | J12: Partial, scattered policies | K12: Low | L12: 2 | M12: 4 | N12: =L12*M12 -> 8 | O12: =IF(N12<=4,"Low",IF(N12<=9,"Moderate",IF(N12<=14,"High","Critical"))) -> Moderate | P12: GRC | Q12: Mitigate | R12: Written information security program; designate Qualified Individual; annual risk assessment
A13: R12 | B13: Unpatched internet-facing systems | C13: ID | D13: External attacker | E13: No vulnerability management program; irregular patching | F13: A1 Portal / A3 Payments | G13: 4 | H13: 4 | I13: =G13*H13 -> 16 | J13: Occasional manual patching | K13: Low | L13: 3 | M13: 4 | N13: =L13*M13 -> 12 | O13: =IF(N13<=4,"Low",IF(N13<=9,"Moderate",IF(N13<=14,"High","Critical"))) -> High | P13: IT | Q13: Mitigate | R13: Vulnerability scanning; patch SLAs; external attack-surface monitoring
... A15: R14 | B15: Shadow IT / unapproved SaaS | C15: GV | D15: Negligent insider | E15: Staff adopt SaaS tools without review; no complete asset inventory | F15: A6 Corporate SaaS | G15: 4 | H15: 3 | I15: =G15*H15 -> 12 | J15: None | K15: None | L15: 3 | M15: 3 | N15: =L15*M15 -> 9 | O15: =IF(N15<=4,"Low",IF(N15<=9,"Moderate",IF(N15<=14,"High","Critical"))) -> Moderate | P15: GRC & IT | Q15: Mitigate | R15: SaaS discovery tooling; software approval process; maintained asset inventory

Sheet Risk Heatmap
B2: Residual Risk Heatmap (count of risks by Likelihood x Impact)
B4: Impact \ Likelihood | C4: 1 | D4: 2 | E4: 3 | F4: 4 | G4: 5
B5: 5 | C5: =COUNTIFS('Risk Register'!$L$2:$L$15,1,'Risk Register'!$M$2:$M$15,5) -> 0 | D5: =COUNTIFS('Risk Register'!$L$2:$L$15,2,'Risk Register'!$M$2:$M$15,5) -> 2 | E5: =COUNTIFS('Risk Register'!$L$2:$L$15,3,'Risk Register'!$M$2:$M$15,5) -> 4 | F5: =COUNTIFS('Risk Register'!$L$2:$L$15,4,'Risk Register'!$M$2:$M$15,5) -> 0 | G5: =COUNTIFS('Risk Register'!$L$2:$L$15,5,'Risk Register'!$M$2:$M$15,5) -> 0
B6: 4 | C6: =COUNTIFS('Risk Register'!$L$2:$L$15,1,'Risk Register'!$M$2:$M$15,4) -> 0 | D6: =COUNTIFS('Risk Register'!$L$2:$L$15,2,'Risk Register'!$M$2:$M$15,4) -> 3 | E6: =COUNTIFS('Risk Register'!$L$2:$L$15,3,'Risk Register'!$M$2:$M$15,4) -> 4 | F6: =COUNTIFS('Risk Register'!$L$2:$L$15,4,'Risk Register'!$M$2:$M$15,4) -> 0 | G6: =COUNTIFS('Risk Register'!$L$2:$L$15,5,'Risk Register'!$M$2:$M$15,4) -> 0
B7: 3 | C7: =COUNTIFS('Risk Register'!$L$2:$L$15,1,'Risk Register'!$M$2:$M$15,3) -> 0 | D7: =COUNTIFS('Risk Register'!$L$2:$L$15,2,'Risk Register'!$M$2:$M$15,3) -> 0 | E7: =COUNTIFS('Risk Register'!$L$2:$L$15,3,'Risk Register'!$M$2:$M$15,3) -> 1 | F7: =COUNTIFS('Risk Register'!$L$2:$L$15,4,'Risk Register'!$M$2:$M$15,3) -> 0 | G7: =COUNTIFS('Risk Register'!$L$2:$L$15,5,'Risk Register'!$M$2:$M$15,3) -> 0
B8: 2 | C8: =COUNTIFS('Risk Register'!$L$2:$L$15,1,'Risk Register'!$M$2:$M$15,2) -> 0 | D8: =COUNTIFS('Risk Register'!$L$2:$L$15,2,'Risk Register'!$M$2:$M$15,2) -> 0 | E8: =COUNTIFS('Risk Register'!$L$2:$L$15,3,'Risk Register'!$M$2:$M$15,2) -> 0 | F8: =COUNTIFS('Risk Register'!$L$2:$L$15,4,'Risk Register'!$M$2:$M$15,2) -> 0 | G8: =COUNTIFS('Risk Register'!$L$2:$L$15,5,'Risk Register'!$M$2:$M$15,2) -> 0
B9: 1 | C9: =COUNTIFS('Risk Register'!$L$2:$L$15,1,'Risk Register'!$M$2:$M$15,1) -> 0 | D9: =COUNTIFS('Risk Register'!$L$2:$L$15,2,'Risk Register'!$M$2:$M$15,1) -> 0 | E9: =COUNTIFS('Risk Register'!$L$2:$L$15,3,'Risk Register'!$M$2:$M$15,1) -> 0 | F9: =COUNTIFS('Risk Register'!$L$2:$L$15,4,'Risk Register'!$M$2:$M$15,1) -> 0 | G9: =COUNTIFS('Risk Register'!$L$2:$L$15,5,'Risk Register'!$M$2:$M$15,1) -> 0
B12: Legend:
B13: Low (1-4)
B14: Moderate (5-9)
B15: High (10-14)
B16: Critical (15-25)

Sheet Dashboard
B2: Risk Dashboard — NorthStar Lending
B4: Residual risk by level
B5: Level | C5: Count
B6: Critical | C6: =COUNTIF('Risk Register'!$O$2:$O$15,"Critical") -> 4
B7: High | C7: =COUNTIF('Risk Register'!$O$2:$O$15,"High") -> 6
B8: Moderate | C8: =COUNTIF('Risk Register'!$O$2:$O$15,"Moderate") -> 4
B9: Low | C9: =COUNTIF('Risk Register'!$O$2:$O$15,"Low") -> 0
B10: Total | C10: =SUM(C6:C9) -> 14
B14: Risks by CSF function
B15: Function | C15: Count
B16: GV | C16: =COUNTIF('Risk Register'!$C$2:$C$15,"GV") -> 3
B17: ID | C17: =COUNTIF('Risk Register'!$C$2:$C$15,"ID") -> 1
B18: PR | C18: =COUNTIF('Risk Register'!$C$2:$C$15,"PR") -> 7
B19: DE | C19: =COUNTIF('Risk Register'!$C$2:$C$15,"DE") -> 1
B20: RS | C20: =COUNTIF('Risk Register'!$C$2:$C$15,"RS") -> 1
B21: RC | C21: =COUNTIF('Risk Register'!$C$2:$C$15,"RC") -> 1

Sheet Quantitative (SLE-ALE)
B2: Quantitative Risk — Annualized Loss (top risk: R03 Insecure API)
B3: Translates a security risk into dollars so control cost can be weighed against risk reduction.
B5: Input / Calculation | C5: Value | D5: Note
B6: Asset value at risk (AV) | C6: 1500000 | D6: Est. value of exposed customer data + business
B7: Exposure Factor (EF) | C7: 0.8 | D7: Fraction of asset value lost if event occurs
B8: Single Loss Expectancy (SLE) | C8: =C6*C7 -> 1200000 | D8: SLE = AV x EF
B9: ARO before controls | C9: 0.4 | D9: Expected events/year without added controls
B10: ALE before controls | C10: =C8*C9 -> 480000 | D10: ALE = SLE x ARO (before)
B11: ARO after controls | C11: 0.1 | D11: Expected events/year with API gateway, WAF, authz
B12: ALE after controls | C12: =C8*C11 -> 120000 | D12: ALE = SLE x ARO (after)
B13: Annual risk reduction | C13: =C10-C12 -> 360000 | D13: ALE before - ALE after
B15: Blue = input you can change; black = formula.
